valeeew/__init__.py
valeeew/cleaning.py
valeeew-0.0.13.dist-info/LICENSE
valeeew-0.0.13.dist-info/METADATA
valeeew-0.0.13.dist-info/WHEEL
valeeew-0.0.13.dist-info/top_level.txt
valeeew-0.0.13.dist-info/RECORD
