Metadata-Version: 2.1
Name: valeeew
Version: 0.0.13
Summary: Toolbox made for DATA manipulation
Home-page: https://github.com/Valeeew/Pack
Author: Valentin MONTEIRO
Author-email: v.monteiro.pro@gmail.com
License: UNKNOWN
Project-URL: Bug Tracker, https://github.com/Valeeew/Pack/issues
Platform: UNKNOWN
Classifier: Programming Language :: Python :: 3
Classifier: License :: OSI Approved :: MIT License
Classifier: Operating System :: OS Independent
Requires-Python: >=3.6
License-File: LICENSE
